README.rst
setup.py
intercom/__init__.py
intercom/base.py
intercom/client.py
intercom/models.py
intercom_python.egg-info/PKG-INFO
intercom_python.egg-info/SOURCES.txt
intercom_python.egg-info/dependency_links.txt
intercom_python.egg-info/requires.txt
intercom_python.egg-info/top_level.txt