Metadata-Version: 1.1
Name: intercom-python
Version: 1.0.5
Summary: A not official python bindings to Intercom API
Home-page: https://github.com/six519/intercom_python
Author: Ferdinand Silva
Author-email: ferdinandsilva@ferdinandsilva.com
License: UNKNOWN
Download-URL: https://github.com/six519/intercom_python
Platform: UNKNOWN
Classifier: Development Status :: 4 - Beta
Classifier: Intended Audience :: Developers
Classifier: Natural Language :: English
Classifier: Programming Language :: Python
Classifier: License :: Freeware
